plotserver_api/__init__.py
plotserver_api-0.0.4.dist-info/LICENSE
plotserver_api-0.0.4.dist-info/METADATA
plotserver_api-0.0.4.dist-info/WHEEL
plotserver_api-0.0.4.dist-info/top_level.txt
plotserver_api-0.0.4.dist-info/RECORD
