Metadata-Version: 2.1
Name: plotserver-api
Version: 0.0.4
Summary: Python API for PlotServer.
Home-page: https://github.com/alartum/plotserver-api
Author: Aleksandr Artemenkov
Author-email: alartum@gmail.com
License: MIT
Platform: UNKNOWN
Classifier: Programming Language :: Python :: 3
Classifier: License :: OSI Approved :: MIT License
Classifier: Operating System :: OS Independent
Requires-Dist: requests
Requires-Dist: cryptography
